polarstar/__init__.py
polarstar/cnc.py
polarstar/plate.py
polarstar/py.typed
polarstar-0.3.0.dist-info/LICENSE
polarstar-0.3.0.dist-info/entry_points.txt
polarstar-0.3.0.dist-info/METADATA
polarstar-0.3.0.dist-info/WHEEL
polarstar-0.3.0.dist-info/RECORD
