Metadata-Version: 2.1
Name: polarstar
Version: 0.3.0
Summary: Polar Star
Home-page: https://github.com/juliogallinaro/PolarStar
License: GPL-3.0
Author: Júlio Gallinaro Maranho and Patrícia Aparecida da Ana
Author-email: juliogallinaro@gmail.com
Requires-Python: >=3.8,<4.0
Classifier: Development Status :: 2 - Pre-Alpha
Classifier: License :: OSI Approved :: GNU General Public License v3 (GPLv3)
Classifier: Programming Language :: Python :: 3
Classifier: Programming Language :: Python :: 3.8
Classifier: Programming Language :: Python :: 3.9
Classifier: Programming Language :: Python :: 3.10
Classifier: Programming Language :: Python :: 3.11
Requires-Dist: click (>=8.0.1)
Requires-Dist: matplotlib (>=3.7,<4.0)
Requires-Dist: numpy (>=1.24,<2.0)
Requires-Dist: pyserial (>=3.0)
Project-URL: Changelog, https://github.com/juliogallinaro/PolarStar/releases
Project-URL: Documentation, https://PolarStar.readthedocs.io
Project-URL: Repository, https://github.com/juliogallinaro/PolarStar
